{
  "version": "0.1.29",
  "updateTime": 1672940005,
  "history": {
    "user": [
      {
        "name": "tourist",
        "newSubmissions": [
          {
            "platform": "codeforces",
            "id": 188074577,
            "pid": "1768E",
            "name": "Partial Sorting",
            "verdict": "OK",
            "creationTime": 1672930911
          },
          {
            "platform": "codeforces",
            "id": 188064629,
            "pid": "1768C",
            "name": "Elemental Decompress",
            "verdict": "OK",
            "creationTime": 1672930149
          },
          {
            "platform": "codeforces",
            "id": 188063758,
            "pid": "1768C",
            "name": "Elemental Decompress",
            "verdict": "WRONG_ANSWER",
            "creationTime": 1672930096
          },
          {
            "platform": "codeforces",
            "id": 188057553,
            "pid": "1768D",
            "name": "Lucky Permutation",
            "verdict": "OK",
            "creationTime": 1672929799
          },
          {
            "platform": "codeforces",
            "id": 188047596,
            "pid": "1768B",
            "name": "Quick Sort",
            "verdict": "OK",
            "creationTime": 1672929439
          },
          {
            "platform": "codeforces",
            "id": 188046502,
            "pid": "1768A",
            "name": "Greatest Convex",
            "verdict": "OK",
            "creationTime": 1672929367
          }
        ],
        "newContests": []
      },
      {
        "name": "jiangly",
        "newSubmissions": [
          {
            "platform": "codeforces",
            "id": 188125976,
            "pid": "1768F",
            "name": "Wonderful Jump",
            "verdict": "TESTING",
            "creationTime": 1672939960
          },
          {
            "platform": "codeforces",
            "id": 188119601,
            "pid": "1768F",
            "name": "Wonderful Jump",
            "verdict": "OK",
            "creationTime": 1672936255
          },
          {
            "platform": "codeforces",
            "id": 188116406,
            "pid": "1768F",
            "name": "Wonderful Jump",
            "verdict": "SKIPPED",
            "creationTime": 1672935817
          },
          {
            "platform": "codeforces",
            "id": 188109154,
            "pid": "1768F",
            "name": "Wonderful Jump",
            "verdict": "MEMORY_LIMIT_EXCEEDED",
            "creationTime": 1672934805
          },
          {
            "platform": "codeforces",
            "id": 188082239,
            "pid": "1768E",
            "name": "Partial Sorting",
            "verdict": "OK",
            "creationTime": 1672931597
          },
          {
            "platform": "codeforces",
            "id": 188068746,
            "pid": "1768D",
            "name": "Lucky Permutation",
            "verdict": "OK",
            "creationTime": 1672930432
          },
          {
            "platform": "codeforces",
            "id": 188064961,
            "pid": "1768C",
            "name": "Elemental Decompress",
            "verdict": "OK",
            "creationTime": 1672930170
          },
          {
            "platform": "codeforces",
            "id": 188053256,
            "pid": "1768B",
            "name": "Quick Sort",
            "verdict": "OK",
            "creationTime": 1672929614
          },
          {
            "platform": "codeforces",
            "id": 188048492,
            "pid": "1768A",
            "name": "Greatest Convex",
            "verdict": "OK",
            "creationTime": 1672929472
          }
        ],
        "newContests": []
      }
    ],
    "contest": []
  },
  "ref": "61f8cd60a42d5eadf172224a54b8b366acf06973"
}