{
  "version": "0.1.29",
  "updateTime": 1661665502,
  "history": {
    "user": [
      {
        "name": "Kenshin2438",
        "newSubmissions": [
          {
            "platform": "codeforces",
            "id": 169908113,
            "pid": "1721E",
            "name": "Prefix Function Queries",
            "verdict": "OK",
            "creationTime": 1661626524
          },
          {
            "platform": "codeforces",
            "id": 169907774,
            "pid": "1721E",
            "name": "Prefix Function Queries",
            "verdict": "OK",
            "creationTime": 1661626263
          }
        ],
        "newContests": []
      }
    ],
    "contest": []
  },
  "ref": "0dd390631a5709481f7bb631564a1e959dbec3ae"
}