{
  "version": "0.1.29",
  "updateTime": 1740721124,
  "history": {
    "user": [
      {
        "name": "tourist",
        "newSubmissions": [
          {
            "platform": "codeforces",
            "id": 308210466,
            "pid": "95D",
            "name": "Horse Races",
            "verdict": "COMPILATION_ERROR",
            "creationTime": 1740700766
          },
          {
            "platform": "codeforces",
            "id": 308208534,
            "pid": "53E",
            "name": "Dead Ends",
            "verdict": "COMPILATION_ERROR",
            "creationTime": 1740697477
          }
        ],
        "newContests": []
      }
    ],
    "contest": []
  },
  "ref": "a38e44c838d2b7ca61eddb8654fb452e2aa62840"
}