{
  "version": "0.1.29",
  "updateTime": 1709055156,
  "history": {
    "user": [
      {
        "name": "jiangly",
        "newSubmissions": [
          {
            "platform": "codeforces",
            "id": 248549111,
            "pid": "1933G",
            "name": "Turtle Magic: Royal Turtle Shell Pattern",
            "verdict": "OK",
            "creationTime": 1709046612
          },
          {
            "platform": "codeforces",
            "id": 248539865,
            "pid": "1933F",
            "name": "Turtle Mission: Robot and the Earthquake",
            "verdict": "OK",
            "creationTime": 1709046147
          },
          {
            "platform": "codeforces",
            "id": 248527450,
            "pid": "1933E",
            "name": "Turtle vs. Rabbit Race: Optimal Trainings",
            "verdict": "OK",
            "creationTime": 1709045572
          },
          {
            "platform": "codeforces",
            "id": 248512706,
            "pid": "1933D",
            "name": "Turtle Tenacity: Continual Mods",
            "verdict": "OK",
            "creationTime": 1709045019
          },
          {
            "platform": "codeforces",
            "id": 248508041,
            "pid": "1933C",
            "name": "Turtle Fingers: Count the Values of k",
            "verdict": "OK",
            "creationTime": 1709044865
          },
          {
            "platform": "codeforces",
            "id": 248502920,
            "pid": "1933B",
            "name": "Turtle Math: Fast Three Task",
            "verdict": "OK",
            "creationTime": 1709044737
          },
          {
            "platform": "codeforces",
            "id": 248496718,
            "pid": "1933A",
            "name": "Turtle Puzzle: Rearrange and Negate",
            "verdict": "OK",
            "creationTime": 1709044630
          }
        ],
        "newContests": []
      }
    ],
    "contest": []
  },
  "ref": "48e7902ddfabeb1239c49857cc9d3a6e02f66f86"
}