{
  "version": "0.1.29",
  "updateTime": 1701797585,
  "history": {
    "user": [
      {
        "name": "jiangly",
        "newSubmissions": [
          {
            "platform": "codeforces",
            "id": 235930993,
            "pid": "1901F",
            "name": "Landscaping",
            "verdict": "OK",
            "creationTime": 1701793006
          },
          {
            "platform": "codeforces",
            "id": 235891459,
            "pid": "1901F",
            "name": "Landscaping",
            "verdict": "RUNTIME_ERROR",
            "creationTime": 1701789187
          },
          {
            "platform": "codeforces",
            "id": 235890222,
            "pid": "1907G",
            "name": "Lights",
            "verdict": "OK",
            "creationTime": 1701789098
          },
          {
            "platform": "codeforces",
            "id": 235883244,
            "pid": "1907F",
            "name": "Shift and Reverse",
            "verdict": "OK",
            "creationTime": 1701788668
          },
          {
            "platform": "codeforces",
            "id": 235877774,
            "pid": "1907E",
            "name": "Good Triples",
            "verdict": "OK",
            "creationTime": 1701788386
          },
          {
            "platform": "codeforces",
            "id": 235875144,
            "pid": "1907D",
            "name": "Jumping Through Segments",
            "verdict": "OK",
            "creationTime": 1701788262
          },
          {
            "platform": "codeforces",
            "id": 235872424,
            "pid": "1907C",
            "name": "Removal of Unattractive Pairs",
            "verdict": "OK",
            "creationTime": 1701788140
          },
          {
            "platform": "codeforces",
            "id": 235870324,
            "pid": "1907B",
            "name": "YetnotherrokenKeoard",
            "verdict": "OK",
            "creationTime": 1701788052
          },
          {
            "platform": "codeforces",
            "id": 235863107,
            "pid": "1907A",
            "name": "Rook",
            "verdict": "OK",
            "creationTime": 1701787781
          },
          {
            "platform": "codeforces",
            "id": 235860574,
            "pid": "1901F",
            "name": "Landscaping",
            "verdict": "RUNTIME_ERROR",
            "creationTime": 1701787679
          },
          {
            "platform": "codeforces",
            "id": 235858013,
            "pid": "1901F",
            "name": "Landscaping",
            "verdict": "RUNTIME_ERROR",
            "creationTime": 1701786685
          },
          {
            "platform": "codeforces",
            "id": 235855997,
            "pid": "1901F",
            "name": "Landscaping",
            "verdict": "WRONG_ANSWER",
            "creationTime": 1701785505
          },
          {
            "platform": "codeforces",
            "id": 235850767,
            "pid": "1901E",
            "name": "Compressed Tree",
            "verdict": "OK",
            "creationTime": 1701782480
          },
          {
            "platform": "codeforces",
            "id": 235850663,
            "pid": "1901E",
            "name": "Compressed Tree",
            "verdict": "WRONG_ANSWER",
            "creationTime": 1701782432
          },
          {
            "platform": "codeforces",
            "id": 235849205,
            "pid": "1901D",
            "name": "Yet Another Monster Fight",
            "verdict": "OK",
            "creationTime": 1701781716
          },
          {
            "platform": "codeforces",
            "id": 235848632,
            "pid": "1901C",
            "name": "Add, Divide and Floor",
            "verdict": "OK",
            "creationTime": 1701781420
          },
          {
            "platform": "codeforces",
            "id": 235847798,
            "pid": "1901B",
            "name": "Chip and Ribbon",
            "verdict": "OK",
            "creationTime": 1701781008
          }
        ],
        "newContests": []
      }
    ],
    "contest": []
  },
  "ref": "ffd20beb4d875c8b738ca041dd33f2a196c4bf40"
}